setup.py
osbuild/__init__.py
osbuild/build.py
osbuild/check.py
osbuild/clean.py
osbuild/command.py
osbuild/config.py
osbuild/distro.py
osbuild/docs.py
osbuild/environ.py
osbuild/git.py
osbuild/main.py
osbuild/run.py
osbuild/shell.py
osbuild/state.py
osbuild/system.py
osbuild/utils.py
osbuild/xvfb.py
osbuild.egg-info/PKG-INFO
osbuild.egg-info/SOURCES.txt
osbuild.egg-info/dependency_links.txt
osbuild.egg-info/requires.txt
osbuild.egg-info/top_level.txt
osbuild/plugins/__init__.py
osbuild/plugins/debian.py
osbuild/plugins/fedora.py
osbuild/plugins/interfaces.py
osbuild/plugins/ubuntu.py
osbuild/plugins/unknown.py
src/sourcestamp.c