Metadata-Version: 1.1
Name: osbuild
Version: 0.27
Summary: Pull, build and test multiple source modules
Home-page: http://github.com/dnarvaez/osbuild
Author: Daniel Narvaez
Author-email: dwnarvaez@gmail.com
License: UNKNOWN
Platform: UNKNOWN
Classifier: License :: OSI Approved :: Apache Software License
Classifier: Programming Language :: Python :: 2
Classifier: Topic :: Software Development :: Build Tools
